Workbook

Sheet Cronograma V2
A1: Cronograma CBS 2027
A2: Reforma Tributária
A3: Última atualização | D3: 46304
E4: Previsto | H4: Real
A5: ID | B5: Marco | C5: Atividade | D5: Responsável | E5: Início | F5: Término | G5: Dias úteis | H5: Início | I5: Término | J5: Status | K5: Observação | L5: Frente
C6: Cronograma geral CBS 2027 | D6: - | E6: =MIN(E7:E132) -> 46266 | F6: =MAX(F7:F132) -> 46477 | G6: =IF(OR(E6="",F6=""),"",NETWORKDAYS(E6,F6,Feriados!$A$2:$A$9)) -> 145
A7: 1 | C7: Planejamento - Tarefa 101363 | E7: =MIN(E8:E19) -> 46288 | F7: =MAX(F8:F19) -> 46346 | G7: =IF(OR(E7="",F7=""),"",NETWORKDAYS(E7,F7,Feriados!$A$2:$A$9)) -> 40 | H7: 46288 | I7: 46297
A8: 1.1 | B8: S | C8: Confirmar a assinatura do contrato da JP Balaban | D8: Kairon Riguete | E8: 46296 | F8: 46310 | G8: =IF(OR(E8="",F8=""),"",NETWORKDAYS(E8,F8,Feriados!$A$2:$A$9)) -> 10 | J8: Não iniciado | L8: 9. Governança/PMO
A9: 1.2 | B9: N | C9: Realizar agendamento semanal de reuniões com os principais envolvidos | D9: Michael Albertoni | E9: 46290 | F9: 46290 | G9: =IF(OR(E9="",F9=""),"",NETWORKDAYS(E9,F9,Feriados!$A$2:$A$9)) -> 1 | H9: 46290 | I9: 46290 | J9: Concluído | L9: 9. Governança/PMO
A10: 1.3 | B10: S | C10: Validar cronograma com o Kairon | D10: Michael Albertoni | E10: 46300 | F10: 46305 | G10: =IF(OR(E10="",F10=""),"",NETWORKDAYS(E10,F10,Feriados!$A$2:$A$9)) -> 5 | J10: Não iniciado | L10: 9. Governança/PMO
A11: 1.4 | B11: N | C11: Revisar a escala de férias de fim de ano das pessoas chave | D11: Michael Albertoni | E11: 46296 | F11: 46346 | G11: =IF(OR(E11="",F11=""),"",NETWORKDAYS(E11,F11,Feriados!$A$2:$A$9)) -> 34 | J11: Não iniciado | K11: Considerar o conflito entre férias coletivas a partir de 20/12 e a virada de regime (levantado na reunião) A Eliandra não para na virada; de 18/11 a 30/11 atende só parcialmente | L11: 9. Governança/PMO
A12: 1.5 | B12: N | C12: Revisar cronograma com o dpto de controladoria e Fiscal | D12: Michael Albertoni | E12: 46288 | F12: 46288 | G12: =IF(OR(E12="",F12=""),"",NETWORKDAYS(E12,F12,Feriados!$A$2:$A$9)) -> 1 | H12: 46288 | I12: 46288 | J12: Concluído | L12: 9. Governança/PMO
A13: 1.6 | B13: N | C13: Revisar o cronograma com o dpto de contratos | D13: Michael Albertoni | E13: 46289 | F13: 46289 | G13: =IF(OR(E13="",F13=""),"",NETWORKDAYS(E13,F13,Feriados!$A$2:$A$9)) -> 1 | H13: 46289 | I13: 46289 | J13: Concluído | L13: 9. Governança/PMO
A14: 1.7 | B14: N | C14: Revisar o cronograma com o dpto Financeiro | D14: Michael Albertoni | E14: 46289 | F14: 46289 | G14: =IF(OR(E14="",F14=""),"",NETWORKDAYS(E14,F14,Feriados!$A$2:$A$9)) -> 1 | H14: 46289 | I14: 46289 | J14: Concluído | L14: 9. Governança/PMO
A15: 1.8 | B15: N | C15: Revisar o cronograma com o dpto de RH | D15: Michael Albertoni | E15: 46304 | F15: 46304 | G15: =IF(OR(E15="",F15=""),"",NETWORKDAYS(E15,F15,Feriados!$A$2:$A$9)) -> 1 | J15: Não iniciado | L15: 9. Governança/PMO
A16: 1.9 | B16: N | C16: Revisar o cronograma com o dpto de Supply Chain (Suprimentos e Frotas) | D16: Michael Albertoni | E16: 46293 | F16: 46293 | G16: =IF(OR(E16="",F16=""),"",NETWORKDAYS(E16,F16,Feriados!$A$2:$A$9)) -> 1 | H16: 46293 | I16: 46293 | J16: Concluído | L16: 9. Governança/PMO
A17: 1.10 | B17: N | C17: Revisar o cronograma com o dpto de T.I | D17: Michael Albertoni | E17: 46293 | F17: 46293 | G17: =IF(OR(E17="",F17=""),"",NETWORKDAYS(E17,F17,Feriados!$A$2:$A$9)) -> 1 | H17: 46293 | I17: 46293 | J17: Concluído | L17: 9. Governança/PMO
A18: 1.11 | B18: N | C18: Revisar o cronograma com a Contabilidade | D18: Michael Albertoni | E18: 46295 | F18: 46295 | G18: =IF(OR(E18="",F18=""),"",NETWORKDAYS(E18,F18,Feriados!$A$2:$A$9)) -> 1 | H18: 46297 | I18: 46297 | J18: Concluído | L18: 9. Governança/PMO
A19: 1.12 | B19: N | C19: Aprovar cronograma e modelo de status do projeto com o patrocinador | D19: Vitória Thums | E19: 46311 | F19: 46311 | G19: =IF(OR(E19="",F19=""),"",NETWORKDAYS(E19,F19,Feriados!$A$2:$A$9)) -> 1 | J19: Não iniciado | L19: 9. Governança/PMO
A20: 2 | C20: Parametrização do ERP Senior - Tarefa 102141 | E20: =MIN(E21:E62) -> 46286 | F20: =MAX(F21:F62) -> 46386 | G20: =IF(OR(E20="",F20=""),"",NETWORKDAYS(E20,F20,Feriados!$A$2:$A$9)) -> 69 | H20: 46286 | I20: 46301
A21: 2.1 | B21: N | C21: Confirmar a build do ERP, a versão do eDocs e o layout 2.00 da NFS-e | D21: Pablo e Kelvin | E21: 46286 | F21: 46290 | G21: =IF(OR(E21="",F21=""),"",NETWORKDAYS(E21,F21,Feriados!$A$2:$A$9)) -> 5 | H21: 46286 | I21: 46290 | J21: Concluído | L21: 4. TI/DF-e
A22: 2.2 | B22: N | C22: Atualizar o ERP e o eDocs com a correção da Senior para as notas de devolução | D22: Pablo e Kelvin | E22: 46291 | F22: 46291 | G22: =IF(OR(E22="",F22=""),"",NETWORKDAYS(E22,F22,Feriados!$A$2:$A$9)) -> 0 | H22: 46291 | I22: 46291 | J22: Concluído | L22: 4. TI/DF-e
A23: 2.3 | B23: N | C23: Mapear os municípios de emissão e a situação de homologação com a Reforma | D23: Pablo e Kelvin | E23: 46286 | F23: 46290 | G23: =IF(OR(E23="",F23=""),"",NETWORKDAYS(E23,F23,Feriados!$A$2:$A$9)) -> 5 | H23: 46286 | I23: 46290 | J23: Concluído | L23: 4. TI/DF-e
A24: 2.4 | B24: N | C24: Atualizar o eDocs e testar a NFS-e em produção restrita nos municípios de maior volume | D24: Pablo | E24: 46291 | F24: 46291 | G24: =IF(OR(E24="",F24=""),"",NETWORKDAYS(E24,F24,Feriados!$A$2:$A$9)) -> 0 | H24: 46291 | I24: 46291 | J24: Concluído | L24: 4. TI/DF-e
A25: 2.5 | B25: N | C25: Parametrizar os cadastros base: NBS, serviço, IndOp, cliente, fornecedor e transações | D25: Pablo e Kelvin | E25: 46286 | F25: 46293 | G25: =IF(OR(E25="",F25=""),"",NETWORKDAYS(E25,F25,Feriados!$A$2:$A$9)) -> 6 | H25: 46286 | I25: 46293 | J25: Concluído | L25: 4. TI/DF-e
A26: 2.6 | B26: N | C26: Parametrizar alíquotas e aplicação da CBS | D26: Pablo e Kelvin | E26: 46288 | F26: 46294 | G26: =IF(OR(E26="",F26=""),"",NETWORKDAYS(E26,F26,Feriados!$A$2:$A$9)) -> 5 | H26: 46294 | I26: 46294 | J26: Concluído | L26: 4. TI/DF-e
A27: 2.7 | B27: N | C27: Habilitar o cálculo da CBS e do IBS filial a filial | D27: Kelvin | E27: 46293 | F27: 46294 | G27: =IF(OR(E27="",F27=""),"",NETWORKDAYS(E27,F27,Feriados!$A$2:$A$9)) -> 2 | H27: 46293 | I27: 46294 | J27: Concluído | L27: 4. TI/DF-e
A28: 2.8 | B28: N | C28: Levantar e validar tela a tela o que já está parametrizado (Saída) | D28: Pablo e Kelvin | E28: 46293 | F28: 46295 | G28: =IF(OR(E28="",F28=""),"",NETWORKDAYS(E28,F28,Feriados!$A$2:$A$9)) -> 3 | H28: 46293 | I28: 46295 | J28: Concluído | L28: 4. TI/DF-e
A29: 2.9 | B29: N | C29: Criar e apresentar o norteador de parametrização por ondas (o que, quais campos, quem preenche, em quantos dias) | D29: Pablo e Kelvin | E29: 46293 | F29: 46296 | G29: =IF(OR(E29="",F29=""),"",NETWORKDAYS(E29,F29,Feriados!$A$2:$A$9)) -> 4 | H29: 46296 | I29: 46296 | J29: Concluído | L29: 4. TI/DF-e
A30: 2.10 | B30: N | C30: Avaliar custo e risco do ambiente de homologação espelhado à produção, ou propor outra estratégia para testar a virada | D30: Pablo e Kelvin | E30: 46296 | F30: 46296 | G30: =IF(OR(E30="",F30=""),"",NETWORKDAYS(E30,F30,Feriados!$A$2:$A$9)) -> 1 | H30: 46296 | I30: 46296 | J30: Concluído | L30: 4. TI/DF-e
A31: 2.11 | B31: N | C31: Testar o robo validador de cenários na Senior com as notas de agosto em diante | D31: Adilson Alberton | E31: 46307 | F31: 46311 | G31: =IF(OR(E31="",F31=""),"",NETWORKDAYS(E31,F31,Feriados!$A$2:$A$9)) -> 4 | H31: 46296 | I31: 46296 | J31: Concluído | L31: 3. Fiscal/CST
A32: 2.12 | B32: N | C32: Resolver a emissão de Lages (tag de informações do município no XML) ou escalar (Senior) | D32: Pablo e Kelvin | E32: 46295 | F32: 46300 | G32: =IF(OR(E32="",F32=""),"",NETWORKDAYS(E32,F32,Feriados!$A$2:$A$9)) -> 4 | H32: 46301 | I32: 46301 | J32: Concluído | L32: 4. TI/DF-e
A33: 2.13 | B33: S | C33: Acompanhar a emissão real das primeiras notas com IBS e CBS destacados | D33: Pablo e Kelvin | G33: =IF(OR(E33="",F33=""),"",NETWORKDAYS(E33,F33,Feriados!$A$2:$A$9)) | J33: Não iniciado | K33: Relatado que as notas já saem com IBS e CBS no XML. Confirmar para marcar como concluída | L33: 4. TI/DF-e
A34: 2.14 | B34: N | C34: Validar se o monitoramento atual de rejeições de DF-e (eDocs) atende como painel do KPI de taxa de rejeição e, se não atender, propor o painel | D34: Pablo e Kelvin | E34: 46308 | F34: 46318 | G34: =IF(OR(E34="",F34=""),"",NETWORKDAYS(E34,F34,Feriados!$A$2:$A$9)) -> 9 | J34: Não iniciado | L34: 4. TI/DF-e
A35: 2.15 | B35: N | C35: Validar se a contingência de emissão da NFS-e (ambiente nacional ou prefeitura fora do ar) já existe e foi testada e, se não, testar | D35: Pablo e Kelvin | E35: 46321 | F35: 46332 | G35: =IF(OR(E35="",F35=""),"",NETWORKDAYS(E35,F35,Feriados!$A$2:$A$9)) -> 9 | J35: Não iniciado | L35: 4. TI/DF-e
A36: 2.16 | B36: N | C36: Enviar a controladoria fiscal a tabela com os contratos e respectivos NBS (Saida) | D36: Andre Desoti | E36: 46300 | F36: 46308 | G36: =IF(OR(E36="",F36=""),"",NETWORKDAYS(E36,F36,Feriados!$A$2:$A$9)) -> 6 | H36: 46302 | J36: Em andamento | L36: 3. Fiscal/CST
A37: 2.17 | B37: N | C37: Cadastrar novos códigos de serviço no erp senior | D37: Robson Carvalho | E37: 46309 | F37: 46311 | G37: =IF(OR(E37="",F37=""),"",NETWORKDAYS(E37,F37,Feriados!$A$2:$A$9)) -> 3 | J37: Não iniciado | L37: 3. Fiscal/CST
C38: Realizar testes de emissão em homologação com os novos códigos de serviço | D38: Robson Carvalho | E38: 46321 | F38: 46325 | G38: =IF(OR(E38="",F38=""),"",NETWORKDAYS(E38,F38,Feriados!$A$2:$A$9)) -> 5
C39: Alterar os códigos de serviço para o faturamento | D39: Robson Carvalho com apoio do Kelvin | E39: 46384 | F39: 46384 | G39: =IF(OR(E39="",F39=""),"",NETWORKDAYS(E39,F39,Feriados!$A$2:$A$9)) -> 1
A40: 2.18 | B40: N | C40: Avaliar o documento criado pelo T.I (2.9) e trazer data do cadastro | D40: CRIAR POR ÁREA | E40: 46308 | F40: 46310 | G40: =IF(OR(E40="",F40=""),"",NETWORKDAYS(E40,F40,Feriados!$A$2:$A$9)) -> 3 | J40: Não iniciado | L40: 4. TI/DF-e
A41: 2.19 | B41: N | C41: Avaliar a criação no cadastro de cliente do Senior o campo de destinatário, carregar a classificação por destinatário e refletir no faturamento e nos relatórios de receita | D41: Pablo e Kelvin | E41: 46329 | F41: 46345 | G41: =IF(OR(E41="",F41=""),"",NETWORKDAYS(E41,F41,Feriados!$A$2:$A$9)) -> 13 | J41: Não iniciado | K41: Depende da classificação dos clientes por destinatário (tarefa removida do cronograma) | L41: 4. TI/DF-e
A42: 2.20 | B42: N | C42: Levantar e validar tela a tela o que já está parametrizado (Entrada) | D42: Pablo e Kelvin | E42: 46293 | F42: 46304 | G42: =IF(OR(E42="",F42=""),"",NETWORKDAYS(E42,F42,Feriados!$A$2:$A$9)) -> 10 | J42: Não iniciado | L42: 4. TI/DF-e
A43: 2.21 | B43: S | C43: Avaliar quem ira validar a base de NBS, serviço e IndOP na entrada | D43: Kairon Riguete | E43: 46304 | F43: 46304 | G43: =IF(OR(E43="",F43=""),"",NETWORKDAYS(E43,F43,Feriados!$A$2:$A$9)) -> 1 | J43: Não iniciado | L43: 3. Fiscal/CST
A44: 2.22 | B44: N | C44: Confirmar se o cadastro de fornecedores atual (na senior) está atendendo a reforma tributária | D44: Pablo e Kelvin | E44: 46304 | F44: 46304 | G44: =IF(OR(E44="",F44=""),"",NETWORKDAYS(E44,F44,Feriados!$A$2:$A$9)) -> 1 | J44: Não iniciado | L44: Suprimentos
A45: 2.23 | B45: N | C45: Definir o reconhecimento do débito referente as vendas para entes governamentais (nota de débito) | D45: Adilson Alberton | E45: 46349 | F45: 46353 | G45: =IF(OR(E45="",F45=""),"",NETWORKDAYS(E45,F45,Feriados!$A$2:$A$9)) -> 5 | J45: Não iniciado | K45: Depende da 2.36. Confirmar com a Senior se a funcionalidade já está liberada | L45: 4. TI/DF-e
A46: 2.24 | B46: N | C46: Parametrizar o cClassTrib e zerar os cenários abertos no analisador | D46: Giselle | G46: =IF(OR(E46="",F46=""),"",NETWORKDAYS(E46,F46,Feriados!$A$2:$A$9)) | J46: Não iniciado | K46: Depende da 7.2 (lista de cClassTrib por cliente, do Contratos) | L46: 3. Fiscal/CST
A47: 2.25 | B47: N | C47: Definir a regra da dupla nota fiscal no setor público: NF de fornecimento na medição atestada (destaque informativo no grupo gTribCompraGov, com redutor de ente) e NF de pagamento na data do recebimento, com a alíquota vigente nessa data e referenciando a NF de fornecimento | D47: Adilson Alberton | E47: 46308 | F47: 46318 | G47: =IF(OR(E47="",F47=""),"",NETWORKDAYS(E47,F47,Feriados!$A$2:$A$9)) -> 9 | J47: Não iniciado | K47: A NF de pagamento é a que gera o débito na apuração assistida. Base para a 2.37, 4.9 e 6.9 | L47: 3. Fiscal/CST
A48: 2.26 | B48: N | C48: Enviar a base de produtos e serviços à Brunetto e receber o cruzamento de NCM/NBS com os anexos da lei | D48: Juliano Liberato | E48: 46304 | F48: 46308 | G48: =IF(OR(E48="",F48=""),"",NETWORKDAYS(E48,F48,Feriados!$A$2:$A$9)) -> 2 | J48: Não iniciado | K48: A Brunetto já mandou essa base no fim de 2025; agora devolve atualizada, com o aproveitamento de crédito de cada item | L48: 3. Fiscal/CST
A49: 2.27 | B49: N | C49: Retornar ao Fiscal a base de produtos com o cruzamento de NCM/NBS de todos os produtos | D49: Brunetto e Juliano | E49: 46308 | F49: 46308 | G49: =IF(OR(E49="",F49=""),"",NETWORKDAYS(E49,F49,Feriados!$A$2:$A$9)) -> 1 | J49: Não iniciado | L49: 4. TI/DF-e
A50: 2.28 | C50: Revisar a base recebida pela Brunetto | D50: Juliano Liberato/Fernando | G50: =IF(OR(E50="",F50=""),"",NETWORKDAYS(E50,F50,Feriados!$A$2:$A$9))
A51: 2.29 | B51: N | C51: Carregar no ERP a base de produtos NBS/CBS | D51: Jober | E51: 46309 | F51: 46325 | G51: =IF(OR(E51="",F51=""),"",NETWORKDAYS(E51,F51,Feriados!$A$2:$A$9)) -> 13 | J51: Não iniciado | L51: 3. Fiscal/CST
A52: 2.30 | B52: S | C52: Enviar à Controladoria (Adilson) a alíquota oficial de CBS assim que for publicada | D52: Eliandra Fraron | E52: 46371 | F52: 46374 | G52: =IF(OR(E52="",F52=""),"",NETWORKDAYS(E52,F52,Feriados!$A$2:$A$9)) -> 4 | J52: Não iniciado | K52: Publicação prevista até 15/12 (Senado); a Eliandra acha que pode sair dia 20. Informação pública: a Controladoria também pode pegar direto | L52: 5. Contábil
A53: 2.31 | B53: N | C53: Atualizar o valor correto de aplicação CBS na senior | D53: Adilson Alberton | E53: 46374 | F53: 46374 | G53: =IF(OR(E53="",F53=""),"",NETWORKDAYS(E53,F53,Feriados!$A$2:$A$9)) -> 1 | J53: Não iniciado | L53: 3. Fiscal/CST
A54: 2.32 | B54: N | C54: Validar na emissão da nota se a alíquota cadastrada está saindo correta | D54: Eliandra Fraron | E54: 46377 | F54: 46379 | G54: =IF(OR(E54="",F54=""),"",NETWORKDAYS(E54,F54,Feriados!$A$2:$A$9)) -> 3 | J54: Não iniciado | K54: Eliandra (02/10): IBS, CBS e cClassTrib já enviados pela Contabilidade à Controladoria | L54: 5. Contábil
A55: 2.33 | B55: N | C55: Revisar as todas as transações do erp Senior referente a Reforma tributária | D55: Adilson Alberton | E55: 46308 | F55: 46374 | G55: =IF(OR(E55="",F55=""),"",NETWORKDAYS(E55,F55,Feriados!$A$2:$A$9)) -> 47 | J55: Não iniciado | L55: 3. Fiscal/CST
A56: 2.34 | B56: N | C56: Parametrizar os layouts de nota de débito e nota de crédito | D56: Adilson Alberton | E56: 46357 | F56: 46374 | G56: =IF(OR(E56="",F56=""),"",NETWORKDAYS(E56,F56,Feriados!$A$2:$A$9)) -> 14 | J56: Não iniciado | L56: 3. Fiscal/CST
A57: 2.35 | C57: Acompanhar o enquadramento da Bogo Locações na segunda onda da NFS-e | D57: Adilson Alberton | E57: 46296 | F57: 46325 | G57: =IF(OR(E57="",F57=""),"",NETWORKDAYS(E57,F57,Feriados!$A$2:$A$9)) -> 21 | H57: 46304 | J57: Em andamento | L57: 3. Fiscal/CST
A58: 2.36 | B58: N | C58: Parametrizar as transações com IBS e CBS (inclusive as de Suprimentos) e a integração contábil nas novas contas | D58: Juliano Liberato | E58: 46328 | F58: 46353 | G58: =IF(OR(E58="",F58=""),"",NETWORKDAYS(E58,F58,Feriados!$A$2:$A$9)) -> 18 | J58: Não iniciado | L58: 3. Fiscal/CST
A59: 2.37 | B59: N | C59: Lançar notas de teste com IBS e CBS na base de homologação, conferindo se a contabilização cai na conta correta | D59: Eliandra Fraron | E59: 46357 | F59: 46363 | G59: =IF(OR(E59="",F59=""),"",NETWORKDAYS(E59,F59,Feriados!$A$2:$A$9)) -> 5 | J59: Não iniciado | L59: 5. Contábil
A60: 2.38 | B60: N | C60: Testar na base de homologação o ciclo completo do setor público | D60: Adilson Alberton | E60: 46374 | F60: 46386 | G60: =IF(OR(E60="",F60=""),"",NETWORKDAYS(E60,F60,Feriados!$A$2:$A$9)) -> 8 | J60: Não iniciado | K60: Depende da 2.37. Serviço de dez/26 pago em jan/27 já cai na CBS plena | L60: 4. TI/DF-e
A61: 2.39 | B61: N | C61: Testar a integração fiscal-contábil das notas de teste e conciliar o razão | D61: Eliandra Fraron | E61: 46372 | F61: 46378 | G61: =IF(OR(E61="",F61=""),"",NETWORKDAYS(E61,F61,Feriados!$A$2:$A$9)) -> 5 | J61: Não iniciado | K61: Prazo de 1 semana: testa, devolve, corrige e testa de novo. Depende das notas de teste na homologação | L61: 5. Contábil
A62: 2.40 | B62: N | C62: Carregar as alíquotas oficiais e homologar a apuração de 2027 | D62: Eliandra Fraron | E62: 46374 | F62: 46374 | G62: =IF(OR(E62="",F62=""),"",NETWORKDAYS(E62,F62,Feriados!$A$2:$A$9)) -> 1 | J62: Não iniciado | K62: Marcada para confirmar. Atenção: em janeiro a apuração de dezembro ainda é PIS e Cofins | L62: 5. Contábil
A63: 3 | C63: Alteração do regime de apuração - Tarefa 102141 | E63: =MIN(E64:E67) -> 46329 | F63: =MAX(F64:F67) -> 46418 | G63: =IF(OR(E63="",F63=""),"",NETWORKDAYS(E63,F63,Feriados!$A$2:$A$9)) -> 61
A64: 3.1 | B64: N | C64: Definir o que muda na virada no faturamento e o que segue no regime atual até o fechamento de dezembro | D64: Giselle | E64: 46357 | F64: 46387 | G64: =IF(OR(E64="",F64=""),"",NETWORKDAYS(E64,F64,Feriados!$A$2:$A$9)) -> 22 | J64: Não iniciado | L64: 3. Fiscal/CST
A65: 3.2 | B65: N | C65: Parametrizar o encerramento do regime cumulativo e a apuração da CBS com crédito e nova transação e forma de contabilização | D65: Adilson Alberton | E65: 46329 | F65: 46367 | G65: =IF(OR(E65="",F65=""),"",NETWORKDAYS(E65,F65,Feriados!$A$2:$A$9)) -> 28 | J65: Não iniciado | L65: 3. Fiscal/CST
A66: 3.3 | B66: N | C66: Testar na base de homologação o fluxo do crédito de IBS e CBS na entrada (a apropriar, a compensar e encontro com o débito) | D66: Adilson Alberton e Eliandra Fraron | E66: 46370 | F66: 46374 | G66: =IF(OR(E66="",F66=""),"",NETWORKDAYS(E66,F66,Feriados!$A$2:$A$9)) -> 5 | J66: Não iniciado | K66: Apuração assistida a partir de 01/01/2027. A Receita ainda não liberou o detalhe de como operacionalizar; na prática, só em janeiro | L66: 3. Fiscal/CST
A67: 3.4 | B67: N | C67: Testar a virada em paralelo com um mês fechado | D67: Adilson Alberton | E67: 46388 | F67: 46418 | G67: =IF(OR(E67="",F67=""),"",NETWORKDAYS(E67,F67,Feriados!$A$2:$A$9)) -> 20 | J67: Não iniciado | K67: Na reunião foi dito que o mês fechado do paralelo é janeiro. Revisar as datas | L67: 3. Fiscal/CST
A68: 4 | C68: Controladoria, Fiscal e Contabilidade - Tarefa 102123 | E68: =MIN(E69:E76) -> 46296 | F68: =MAX(F69:F76) -> 46444 | G68: =IF(OR(E68="",F68=""),"",NETWORKDAYS(E68,F68,Feriados!$A$2:$A$9)) -> 100
A69: 4.1 | B69: N | C69: Confirmar por escrito o tratamento do crédito de vale-alimentação e refeição após a LC 227/2026 | D69: JP Balaban | E69: 46311 | F69: 46311 | G69: =IF(OR(E69="",F69=""),"",NETWORKDAYS(E69,F69,Feriados!$A$2:$A$9)) -> 1 | J69: Não iniciado | L69: 1. Benefícios
A70: 4.2 | B70: N | C70: Validar a lista de produtos e serviços que geram crédito de CBS | D70: JP Balaban | E70: 46311 | F70: 46311 | G70: =IF(OR(E70="",F70=""),"",NETWORKDAYS(E70,F70,Feriados!$A$2:$A$9)) -> 1 | J70: Não iniciado | K70: Depois da assinatura do contrato e parametrização do sistema | L70: 3. Fiscal/CST
A71: 4.3 | B71: N | C71: Definir, transação a transação, o que é creditável na entrada (depende da 4.2) | D71: Giselle | E71: 46314 | F71: 46318 | G71: =IF(OR(E71="",F71=""),"",NETWORKDAYS(E71,F71,Feriados!$A$2:$A$9)) -> 5 | J71: Não iniciado | L71: 3. Fiscal/CST
A72: 4.4 | B72: N | C72: Nomear o responsável pelo controle de créditos de IBS e CBS | D72: Juliano Liberato | E72: 46296 | F72: 46325 | G72: =IF(OR(E72="",F72=""),"",NETWORKDAYS(E72,F72,Feriados!$A$2:$A$9)) -> 21 | J72: Não iniciado | L72: 3. Fiscal/CST
A73: 4.5 | B73: N | C73: Levantar e documentar os saldos de PIS e Cofins com memória de cálculo | D73: Adilson Alberton com JB balaban | E73: 46357 | F73: 46387 | G73: =IF(OR(E73="",F73=""),"",NETWORKDAYS(E73,F73,Feriados!$A$2:$A$9)) -> 22 | J73: Não iniciado | L73: 5. Contábil
A74: 4.6 | B74: N | C74: Adequar o plano de contas e confirmar a abertura das contas de IBS e CBS | D74: Eliandra Fraron | E74: 46308 | F74: 46325 | G74: =IF(OR(E74="",F74=""),"",NETWORKDAYS(E74,F74,Feriados!$A$2:$A$9)) -> 14 | J74: Não iniciado | K74: Pré-requisito da 2.32. A 2.31 cita que a Eliandra cria as contas no fiscal de outubro | L74: 5. Contábil
A75: 4.7 | B75: N | C75: Realizar o inventário do estoque em 31/12/2026 | D75: Eliandra Fraron e Fernando Gomes | E75: 46357 | F75: 46387 | G75: =IF(OR(E75="",F75=""),"",NETWORKDAYS(E75,F75,Feriados!$A$2:$A$9)) -> 22 | J75: Não iniciado | K75: Atenção ao conflito com as férias coletivas a partir de 20/12 (1.4) | L75: 5. Contábil
A76: 4.8 | B76: N | C76: Fechar a primeira apuração real de CBS (Refente ao Mês 01/2027) | D76: Eliandra Fraron | E76: 46419 | F76: 46444 | G76: =IF(OR(E76="",F76=""),"",NETWORKDAYS(E76,F76,Feriados!$A$2:$A$9)) -> 18 | J76: Não iniciado | L76: 5. Contábil
A77: 5 | C77: Suprimentos - Tarefa 102147 | E77: =MIN(E78:E96) -> 46266 | F77: =MAX(F78:F96) -> 46444 | G77: =IF(OR(E77="",F77=""),"",NETWORKDAYS(E77,F77,Feriados!$A$2:$A$9)) -> 122 | H77: =MIN(H78:H96) -> 46286 | I77: =MAX(I78:I96) -> 46293
A78: 5.1 | B78: S | C78: Orientar os fornecedores estratégicos do Simples sobre a opção pelo regime regular (Facilities e Foods) | D78: Fernando Gomes | E78: 46286 | F78: 46293 | G78: =IF(OR(E78="",F78=""),"",NETWORKDAYS(E78,F78,Feriados!$A$2:$A$9)) -> 6 | H78: 46286 | I78: 46293 | J78: Concluído | L78: Suprimentos
A79: 5.2 | B79: S | C79: Orientar os fornecedores estratégicos do Simples sobre a opção pelo regime regular (Frota) | D79: Eduardo Santos | E79: 46286 | F79: 46293 | G79: =IF(OR(E79="",F79=""),"",NETWORKDAYS(E79,F79,Feriados!$A$2:$A$9)) -> 6 | H79: 46286 | I79: 46293 | J79: Concluído | L79: Suprimentos
A80: 5.3 | B80: N | C80: Consolidar a base de fornecedores por regime tributário e negócio: Facilities e Foods | D80: Fernando Gomes | E80: 46266 | F80: 46325 | G80: =IF(OR(E80="",F80=""),"",NETWORKDAYS(E80,F80,Feriados!$A$2:$A$9)) -> 43 | J80: Em andamento | K80: Formulário enviado aos fornecedores; nem todos responderam. Base para a 5.12 | L80: Suprimentos
A81: 5.4 | B81: N | C81: Consolidar a base de fornecedores por regime tributário e negócio: Frota | D81: Eduardo Santos | E81: 46266 | F81: 46325 | G81: =IF(OR(E81="",F81=""),"",NETWORKDAYS(E81,F81,Feriados!$A$2:$A$9)) -> 43 | J81: Em andamento | K81: Formulário enviado aos fornecedores; nem todos responderam. Base para a 5.12 | L81: Suprimentos
A82: 5.5 | B82: N | C82: Separar os fornecedores do Simples Nacional (Facilities e Foods) | D82: Fernando Gomes | E82: 46310 | F82: 46325 | G82: =IF(OR(E82="",F82=""),"",NETWORKDAYS(E82,F82,Feriados!$A$2:$A$9)) -> 12 | J82: Não iniciado | L82: Suprimentos
A83: 5.6 | B83: N | C83: Separar os fornecedores do Simples Nacional (Frota) | D83: Eduardo Santos | E83: 46293 | F83: 46325 | G83: =IF(OR(E83="",F83=""),"",NETWORKDAYS(E83,F83,Feriados!$A$2:$A$9)) -> 24 | J83: Em andamento | L83: Suprimentos
A84: 5.7 | B84: N | C84: Enviar ao Financeiro a lista de fornecedores com o regime tributário e o impacto de IBS e CBS de cada um | D84: Fernando Gomes e Eduardo Santos | E84: 46339 | F84: 46339 | G84: =IF(OR(E84="",F84=""),"",NETWORKDAYS(E84,F84,Feriados!$A$2:$A$9)) -> 1 | J84: Não iniciado | K84: Depois das 5.3 e 5.4. Classificação com orientação da Controladoria (Juliano Liberato). Pré-requisito da 6.6, 6.2 e 6.5 | L84: Suprimentos
A85: 5.8 | B85: N | C85: Definir com os fornecedores a rotina de recolhimento para evitar pagamento em duplicidade | D85: Brunetto e Suprimentos | E85: 46329 | F85: 46374 | G85: =IF(OR(E85="",F85=""),"",NETWORKDAYS(E85,F85,Feriados!$A$2:$A$9)) -> 33 | J85: Não iniciado | K85: Depende da reunião com a Brunetto (1.11). Não é especialidade de Suprimentos; a ferramenta da JP Balaban pode trazer essa base | L85: 5. Contábil
A86: 5.9 | B86: N | C86: Calcular o crédito que deixaremos de aproveitar com os fornecedores do Simples não optantes | D86: Fernando Gomes | E86: 46419 | F86: 46444 | G86: =IF(OR(E86="",F86=""),"",NETWORKDAYS(E86,F86,Feriados!$A$2:$A$9)) -> 18 | J86: Não iniciado | K86: Depende da nova consulta à Receita (06/11), feita depois do comunicado de 30/10 | L86: Suprimentos
A87: 5.10 | B87: N | C87: Levantar se é possível concentrar as compras até 20/12 (Suprimentos e Foods) | D87: Fernando Gomes | E87: 46349 | F87: 46356 | G87: =IF(OR(E87="",F87=""),"",NETWORKDAYS(E87,F87,Feriados!$A$2:$A$9)) -> 6 | J87: Não iniciado | K87: Foods, que é o maior volume, deve conseguir. Facilities tem contratos de transporte que exigem nota. Estimativa, não número exato | L87: Suprimentos
A88: 5.11 | B88: N | C88: Levantar se é possível concentrar as compras até 20/12 (Frota) | D88: Eduardo Santos | E88: 46349 | F88: 46356 | G88: =IF(OR(E88="",F88=""),"",NETWORKDAYS(E88,F88,Feriados!$A$2:$A$9)) -> 6 | J88: Não iniciado | K88: Aluguel dá para adiantar; manutenção só em parte; abastecimento e conserto emergencial não têm como | L88: Suprimentos
A89: 5.12 | B89: N | C89: Definir a data de corte de compras garantindo o recebimento até 20/12 (Suprimentos e Foods) | D89: Fernando Gomes | E89: 46357 | F89: 46357 | G89: =IF(OR(E89="",F89=""),"",NETWORKDAYS(E89,F89,Feriados!$A$2:$A$9)) -> 1 | J89: Não iniciado | K89: Depende da 5.7. Substitui a antiga 4.14 (fechamento de dezembro e corte de 31/12) | L89: Suprimentos
A90: 5.13 | B90: N | C90: Definir a data de corte de compras garantindo o recebimento até 20/12 (Frota) | D90: Eduardo Santos | E90: 46357 | F90: 46357 | G90: =IF(OR(E90="",F90=""),"",NETWORKDAYS(E90,F90,Feriados!$A$2:$A$9)) -> 1 | J90: Não iniciado | K90: Depende da 5.8 | L90: Suprimentos
A91: 5.14 | B91: N | C91: Elaborar e publicar a política de compras por preço líquido de crédito | D91: Fernando Gomes | E91: 46372 | F91: 46387 | G91: =IF(OR(E91="",F91=""),"",NETWORKDAYS(E91,F91,Feriados!$A$2:$A$9)) -> 11 | J91: Não iniciado | K91: Depende das alíquotas oficiais (Senado, até 15/12) | L91: Suprimentos
A92: 5.15 | B92: N | C92: Renegociar os itens de maior valor da curva ABC dos fornecedores que mais compramos | D92: Fernando Gomes | E92: 46372 | F92: 46387 | G92: =IF(OR(E92="",F92=""),"",NETWORKDAYS(E92,F92,Feriados!$A$2:$A$9)) -> 11 | J92: Não iniciado | K92: A renegociação já é rotina; aqui entra o novo preço com a alíquota oficial | L92: Suprimentos
A93: 5.16 | B93: N | C93: Orientar e Acompanhar Suprimentos e Frota a lançar o IBS e a CBS da nota de entrada exatamente como vêm do fornecedor, sem ajuste manual | D93: Juliano Liberato, com Fernando Gomes e Eduardo Santos | E93: 46357 | F93: 46374 | G93: =IF(OR(E93="",F93=""),"",NETWORKDAYS(E93,F93,Feriados!$A$2:$A$9)) -> 14 | J93: Não iniciado | K93: Na apuração assistida a Receita usa o que está na nota do fornecedor; ajuste manual no lançamento não entra. Vale a partir de 01/01/2027 | L93: 3. Fiscal/CST
A94: 5.17 | B94: N | C94: Avaliar a contratação ou o desenvolvimento de ferramenta de análise de cotações por preço líquido de crédito | D94: Fernando Gomes | E94: 46329 | F94: 46339 | G94: =IF(OR(E94="",F94=""),"",NETWORKDAYS(E94,F94,Feriados!$A$2:$A$9)) -> 9 | J94: Não iniciado | L94: Suprimentos
A95: 5.18 | B95: N | C95: Revisar janela de opção do Simples dos fornecedores(Suprimentos e Foods) | D95: Fernando Gomes | E95: 46419 | F95: 46444 | G95: =IF(OR(E95="",F95=""),"",NETWORKDAYS(E95,F95,Feriados!$A$2:$A$9)) -> 18 | J95: Não iniciado | K95: Nova rodada com os fornecedores que não optaram; efeito no 2º semestre de 2027 | L95: Suprimentos
A96: 5.19 | B96: N | C96: Revisar janela de opção do Simples dos fornecedores (Frota) | D96: Eduardo Santos | E96: 46419 | F96: 46444 | G96: =IF(OR(E96="",F96=""),"",NETWORKDAYS(E96,F96,Feriados!$A$2:$A$9)) -> 18 | J96: Não iniciado | K96: Nova rodada com os fornecedores que não optaram; efeito no 2º semestre de 2027 | L96: Suprimentos
A97: 6 | C97: Financeiro - Tarefa 102137 (Split payment prorrogado para 2028) | E97: =MIN(E98:E106) -> 46296 | F97: =MAX(F98:F106) -> 46477 | G97: =IF(OR(E97="",F97=""),"",NETWORKDAYS(E97,F97,Feriados!$A$2:$A$9)) -> 123
A98: 6.1 | B98: N | C98: Gerar o relatório de contas a receber com os principais clientes (maiores, médios e menores) e as datas de pagamento atuais | D98: Lucas Moraes | E98: 46296 | F98: 46304 | G98: =IF(OR(E98="",F98=""),"",NETWORKDAYS(E98,F98,Feriados!$A$2:$A$9)) -> 7 | J98: Não iniciado | L98: 8. Financeiro/Caixa
A99: 6.2 | B99: N | C99: Levantar os principais fornecedores e as datas de pagamento considerando o crédito de CBS e IBS do estudo da Controladoria e de Suprimentos | D99: Lucas Moraes | G99: =IF(OR(E99="",F99=""),"",NETWORKDAYS(E99,F99,Feriados!$A$2:$A$9)) | J99: Não iniciado | K99: O Financeiro não enxerga a tributação do fornecedor no contas a pagar. Prorrogada até a entrega da 5.12; datas a definir | L99: 8. Financeiro/Caixa
A100: 6.3 | C100: Levantar o faturamento público de nov e dez/26 com recebimento previsto em 2027 (parcela que já cai na CBS plena pelo fato gerador no pagamento) | D100: Lucas Moraes | E100: 46329 | F100: 46339 | G100: =IF(OR(E100="",F100=""),"",NETWORKDAYS(E100,F100,Feriados!$A$2:$A$9)) -> 9 | J100: Não iniciado | L100: 8. Financeiro/Caixa
...

Sheet Cronograma
A1: Cronograma CBS 2027
A2: Reforma Tributária
A3: Última atualização | D3: 46290
E4: Previsto | H4: Real
A5: ID | B5: Marco | C5: Atividade | D5: Responsável | E5: Início | F5: Término | G5: Dias úteis | H5: Início | I5: Término | J5: Status | K5: Observação | L5: Frente
A6: 1 | B6: N | C6: Planejamento - Tarefa 101363 | E6: =MIN(E7:E19) -> 46286 | F6: =MAX(F7:F19) -> 46304 | G6: =IF(OR(E6="",F6=""),"",NETWORKDAYS(E6,F6,Feriados!$A$2:$A$9)) -> 15 | H6: =MIN(H7:H19) -> 46288 | I6: =MAX(I7:I19) -> 46297
A7: 1.1 | B7: S | C7: Confirmar a assinatura do contrato da JP Balaban | D7: Kairon Riguete | E7: 46296 | F7: 46304 | G7: =IF(OR(E7="",F7=""),"",NETWORKDAYS(E7,F7,Feriados!$A$2:$A$9)) -> 7 | J7: Não iniciado | L7: 9. Governança/PMO
A8: 1.2 | B8: N | C8: Realizar agendamento semanal de reuniões com os principais envolvidos | D8: Michael Albertoni | E8: 46290 | F8: 46290 | G8: =IF(OR(E8="",F8=""),"",NETWORKDAYS(E8,F8,Feriados!$A$2:$A$9)) -> 1 | H8: 46290 | I8: 46290 | J8: Concluído | L8: 9. Governança/PMO
A9: 1.3 | B9: S | C9: Validar cronograma com o Kairon | D9: Michael Albertoni | E9: 46286 | F9: 46304 | G9: =IF(OR(E9="",F9=""),"",NETWORKDAYS(E9,F9,Feriados!$A$2:$A$9)) -> 15 | J9: Não iniciado | L9: 9. Governança/PMO
A10: 1.4 | B10: N | C10: Revisar a escala de férias de fim de ano das pessoas chave | D10: Juliano Liberato | E10: 46296 | F10: 46304 | G10: =IF(OR(E10="",F10=""),"",NETWORKDAYS(E10,F10,Feriados!$A$2:$A$9)) -> 7 | J10: Não iniciado | K10: Considerar o conflito entre férias coletivas a partir de 20/12 e a virada de regime (levantado na reunião) A Eliandra não para na virada; de 18/11 a 30/11 atende só parcialmente | L10: 9. Governança/PMO
A11: 1.5 | B11: N | C11: Revisar cronograma com o dpto de controladoria e Fiscal | D11: Michael Albertoni | E11: 46288 | F11: 46288 | G11: =IF(OR(E11="",F11=""),"",NETWORKDAYS(E11,F11,Feriados!$A$2:$A$9)) -> 1 | H11: 46288 | I11: 46288 | J11: Concluído | L11: 9. Governança/PMO
A12: 1.6 | B12: N | C12: Revisar o cronograma com o dpto de contratos | D12: Michael Albertoni | E12: 46289 | F12: 46289 | G12: =IF(OR(E12="",F12=""),"",NETWORKDAYS(E12,F12,Feriados!$A$2:$A$9)) -> 1 | H12: 46289 | I12: 46289 | J12: Concluído | L12: 9. Governança/PMO
A13: 1.7 | B13: N | C13: Revisar o cronograma com o dpto Financeiro | D13: Michael Albertoni | E13: 46289 | F13: 46289 | G13: =IF(OR(E13="",F13=""),"",NETWORKDAYS(E13,F13,Feriados!$A$2:$A$9)) -> 1 | H13: 46289 | I13: 46289 | J13: Concluído | L13: 9. Governança/PMO
A14: 1.8 | B14: N | C14: Revisar o cronograma com o dpto Comercial | D14: Michael Albertoni | E14: 46302 | F14: 46304 | G14: =IF(OR(E14="",F14=""),"",NETWORKDAYS(E14,F14,Feriados!$A$2:$A$9)) -> 3 | J14: Não iniciado | L14: 9. Governança/PMO
A15: 1.9 | B15: N | C15: Revisar o cronograma com o dpto de RH | D15: Michael Albertoni | E15: 46302 | F15: 46304 | G15: =IF(OR(E15="",F15=""),"",NETWORKDAYS(E15,F15,Feriados!$A$2:$A$9)) -> 3 | J15: Não iniciado | L15: 9. Governança/PMO
A16: 1.10 | B16: N | C16: Revisar o cronograma com o dpto de Supply Chain (Suprimentos e Frotas) | D16: Michael Albertoni | E16: 46293 | F16: 46293 | G16: =IF(OR(E16="",F16=""),"",NETWORKDAYS(E16,F16,Feriados!$A$2:$A$9)) -> 1 | H16: 46293 | I16: 46293 | J16: Concluído | L16: 9. Governança/PMO
A17: 1.11 | B17: N | C17: Revisar o cronograma com o dpto de T.I | D17: Michael Albertoni | E17: 46293 | F17: 46293 | G17: =IF(OR(E17="",F17=""),"",NETWORKDAYS(E17,F17,Feriados!$A$2:$A$9)) -> 1 | H17: 46293 | I17: 46293 | J17: Concluído | L17: 9. Governança/PMO
A18: 1.12 | B18: N | C18: Revisar o cronograma com a Contabilidade | D18: Michael Albertoni | E18: 46295 | F18: 46295 | G18: =IF(OR(E18="",F18=""),"",NETWORKDAYS(E18,F18,Feriados!$A$2:$A$9)) -> 1 | H18: 46297 | I18: 46297 | J18: Concluído | L18: 9. Governança/PMO
A19: 1.13 | B19: N | C19: Revisar o cronograma com o Patrocinador e aprovar o painel mensal de KPIs ao Conselho (rejeição de DF-e, captura de créditos por categoria em R$ e %, claims protocolados e deferidos em 90 dias, aderência ao cronograma, desvio orçamentário e metas por empresa: CO, Grabin, Terceirize e Bogo) | D19: Michael Albertoni | E19: 46304 | F19: 46304 | G19: =IF(OR(E19="",F19=""),"",NETWORKDAYS(E19,F19,Feriados!$A$2:$A$9)) -> 1 | J19: Não iniciado | L19: 9. Governança/PMO
A20: 2 | C20: Parametrização do ERP Senior - Tarefa 102141 | E20: =MIN(E21:E56) -> 46286 | F20: =MAX(F21:F56) -> 46386 | G20: =IF(OR(E20="",F20=""),"",NETWORKDAYS(E20,F20,Feriados!$A$2:$A$9)) -> 69 | H20: =MIN(H21:H63) -> 46286 | I20: =MAX(I21:I63) -> 46301
A21: 2.1 | B21: N | C21: Confirmar a build do ERP, a versão do eDocs e o layout 2.00 da NFS-e | D21: Kelvin | E21: 46286 | F21: 46290 | G21: =IF(OR(E21="",F21=""),"",NETWORKDAYS(E21,F21,Feriados!$A$2:$A$9)) -> 5 | H21: 46286 | I21: 46290 | J21: Concluído | L21: 4. TI/DF-e
A22: 2.2 | B22: N | C22: Atualizar o ERP e o eDocs com a correção da Senior para as notas de devolução | D22: Pablo e Kelvin | E22: 46291 | F22: 46291 | G22: =IF(OR(E22="",F22=""),"",NETWORKDAYS(E22,F22,Feriados!$A$2:$A$9)) -> 0 | H22: 46291 | I22: 46291 | J22: Concluído | L22: 4. TI/DF-e
A23: 2.3 | B23: N | C23: Mapear os municípios de emissão e a situação de homologação com a Reforma | D23: Pablo | E23: 46286 | F23: 46290 | G23: =IF(OR(E23="",F23=""),"",NETWORKDAYS(E23,F23,Feriados!$A$2:$A$9)) -> 5 | H23: 46286 | I23: 46290 | J23: Concluído | L23: 4. TI/DF-e
A24: 2.4 | B24: N | C24: Levantar e validar tela a tela o que já está parametrizado (Saída) | D24: Pablo | E24: 46293 | F24: 46295 | G24: =IF(OR(E24="",F24=""),"",NETWORKDAYS(E24,F24,Feriados!$A$2:$A$9)) -> 3 | H24: 46293 | I24: 46295 | J24: Concluído | L24: 4. TI/DF-e
A25: 2.5 | B25: N | C25: Levantar e validar tela a tela o que já está parametrizado (Entrada) | D25: Pablo e Kelvin | E25: 46293 | F25: 46304 | G25: =IF(OR(E25="",F25=""),"",NETWORKDAYS(E25,F25,Feriados!$A$2:$A$9)) -> 10 | J25: Não iniciado | L25: 4. TI/DF-e
A26: 2.6 | B26: N | C26: Avaliar a migração das prefeituras de Lages para o ambiente nacional | D26: Kelvin | E26: 46301 | F26: 46301 | G26: =IF(OR(E26="",F26=""),"",NETWORKDAYS(E26,F26,Feriados!$A$2:$A$9)) -> 1 | H26: 46301 | I26: 46301 | J26: Concluído | L26: 4. TI/DF-e
A27: 2.7 | B27: N | C27: Resolver a emissão de Lages (tag de informações do município no XML) ou escalar (Senior) | D27: Pablo e Kelvin | E27: 46293 | F27: 46294 | G27: =IF(OR(E27="",F27=""),"",NETWORKDAYS(E27,F27,Feriados!$A$2:$A$9)) -> 2 | H27: 46295 | I27: 46295 | J27: Concluído | L27: 4. TI/DF-e
A28: 2.8 | B28: N | C28: Parametrizar os cadastros base: NBS, serviço, IndOp, cliente, fornecedor e transações | D28: Pablo | E28: 46286 | F28: 46293 | G28: =IF(OR(E28="",F28=""),"",NETWORKDAYS(E28,F28,Feriados!$A$2:$A$9)) -> 6 | H28: 46286 | I28: 46293 | J28: Concluído | L28: 4. TI/DF-e
A29: 2.9 | B29: N | C29: Enviar a controladoria fiscal a tabela com os contratos e respectivos NBS (Saida) | D29: Andre Desoti | E29: 46300 | F29: 46304 | G29: =IF(OR(E29="",F29=""),"",NETWORKDAYS(E29,F29,Feriados!$A$2:$A$9)) -> 5 | H29: 46302 | J29: Em andamento | L29: 3. Fiscal/CST
A30: 2.10 | B30: N | C30: Validar os cadastros base de NBS, serviço e IndOP (Saida) | D30: Adilson Alberton | E30: 46307 | F30: 46311 | G30: =IF(OR(E30="",F30=""),"",NETWORKDAYS(E30,F30,Feriados!$A$2:$A$9)) -> 4 | J30: Não iniciado | L30: 3. Fiscal/CST
A31: 2.11 | B31: S | C31: Avaliar quem ira validar a base de NBS, serviço e IndOP na entrada | D31: Kairon Riguete | E31: 46314 | F31: 46324 | G31: =IF(OR(E31="",F31=""),"",NETWORKDAYS(E31,F31,Feriados!$A$2:$A$9)) -> 9 | J31: Não iniciado | L31: 3. Fiscal/CST
A32: 2.12 | B32: N | C32: Validar fornecedor | D32: Fernando Gomes | E32: 46325 | F32: 46339 | G32: =IF(OR(E32="",F32=""),"",NETWORKDAYS(E32,F32,Feriados!$A$2:$A$9)) -> 10 | J32: Não iniciado | L32: Suprimentos
A33: 2.13 | B33: N | C33: Validar transações | D33: Juliano Liberato | E33: 46296 | F33: 46325 | G33: =IF(OR(E33="",F33=""),"",NETWORKDAYS(E33,F33,Feriados!$A$2:$A$9)) -> 21 | J33: Não iniciado | L33: 3. Fiscal/CST
A34: 2.14 | B34: N | C34: Parametrizar alíquotas e aplicação da CBS | D34: Kelvin | E34: 46288 | F34: 46294 | G34: =IF(OR(E34="",F34=""),"",NETWORKDAYS(E34,F34,Feriados!$A$2:$A$9)) -> 5 | H34: 46294 | I34: 46294 | J34: Concluído | L34: 4. TI/DF-e
A35: 2.15 | B35: S | C35: Enviar à Controladoria (Adilson) a alíquota oficial de CBS assim que for publicada | D35: Eliandra Fraron | E35: 46371 | F35: 46374 | G35: =IF(OR(E35="",F35=""),"",NETWORKDAYS(E35,F35,Feriados!$A$2:$A$9)) -> 4 | J35: Não iniciado | K35: Publicação prevista até 15/12 (Senado); a Eliandra acha que pode sair dia 20. Informação pública: a Controladoria também pode pegar direto | L35: 5. Contábil
A36: 2.16 | B36: N | C36: Informar o valor correto de aplicação CBS na senior | D36: Adilson Alberton | E36: 46374 | F36: 46374 | G36: =IF(OR(E36="",F36=""),"",NETWORKDAYS(E36,F36,Feriados!$A$2:$A$9)) -> 1 | J36: Não iniciado | L36: 3. Fiscal/CST
A37: 2.17 | B37: N | C37: Validar na emissão da nota se a alíquota cadastrada pelo Adilson está saindo correta | D37: Eliandra Fraron | E37: 46377 | F37: 46379 | G37: =IF(OR(E37="",F37=""),"",NETWORKDAYS(E37,F37,Feriados!$A$2:$A$9)) -> 3 | J37: Não iniciado | K37: Eliandra (02/10): IBS, CBS e cClassTrib já enviados pela Contabilidade à Controladoria | L37: 5. Contábil
A38: 2.18 | B38: N | C38: Parametrizar o cClassTrib e zerar os cenários abertos no analisador | D38: Giselle | E38: 46300 | F38: 46311 | G38: =IF(OR(E38="",F38=""),"",NETWORKDAYS(E38,F38,Feriados!$A$2:$A$9)) -> 9 | J38: Não iniciado | K38: Depende da 7.3 (lista de cClassTrib por cliente, do Contratos) | L38: 3. Fiscal/CST
A39: 2.19 | B39: N | C39: Habilitar o cálculo da CBS e do IBS filial a filial | D39: Kelvin | E39: 46293 | F39: 46294 | G39: =IF(OR(E39="",F39=""),"",NETWORKDAYS(E39,F39,Feriados!$A$2:$A$9)) -> 2 | H39: 46293 | I39: 46294 | J39: Concluído | L39: 4. TI/DF-e
A40: 2.20 | B40: N | C40: Atualizar o eDocs e testar a NFS-e em produção restrita nos municípios de maior volume | D40: Pablo | E40: 46291 | F40: 46291 | G40: =IF(OR(E40="",F40=""),"",NETWORKDAYS(E40,F40,Feriados!$A$2:$A$9)) -> 0 | H40: 46291 | I40: 46291 | J40: Concluído | L40: 4. TI/DF-e
A41: 2.21 | B41: N | C41: Testar o robo validador de cenários na Senior com as notas de agosto em diante | D41: Adilson Alberton | E41: 46307 | F41: 46311 | G41: =IF(OR(E41="",F41=""),"",NETWORKDAYS(E41,F41,Feriados!$A$2:$A$9)) -> 4 | H41: 46296 | I41: 46296 | J41: Concluído | L41: 3. Fiscal/CST
A42: 2.22 | B42: N | C42: Apresentar o norteador de parametrização por ondas (o que, quais campos, quem preenche, em quantos dias) | D42: Pablo e Kelvin | E42: 46293 | F42: 46296 | G42: =IF(OR(E42="",F42=""),"",NETWORKDAYS(E42,F42,Feriados!$A$2:$A$9)) -> 4 | H42: 46296 | I42: 46296 | J42: Concluído | L42: 4. TI/DF-e
A43: 2.23 | B43: N | C43: Avaliar possibilidade de listar os cadastros que o Contratos precisa fazer para a nota de saída, com prazo para cada um | D43: Pablo e Kelvin | E43: 46296 | F43: 46325 | G43: =IF(OR(E43="",F43=""),"",NETWORKDAYS(E43,F43,Feriados!$A$2:$A$9)) -> 21 | J43: Não iniciado | L43: 4. TI/DF-e
A44: 2.24 | B44: N | C44: Levantamento na senior para parametrização dos produtos ativos (NBS e NCM), priorizando os de maior giro | D44: Pablo e Kelvin | E44: 46293 | F44: 46304 | G44: =IF(OR(E44="",F44=""),"",NETWORKDAYS(E44,F44,Feriados!$A$2:$A$9)) -> 10 | J44: Não iniciado | L44: 4. TI/DF-e
A45: 2.25 | B45: N | C45: Enviar a base de produtos à Brunetto e receber o cruzamento de NCM com os anexos da lei | D45: Juliano Liberato | E45: 46302 | F45: 46304 | G45: =IF(OR(E45="",F45=""),"",NETWORKDAYS(E45,F45,Feriados!$A$2:$A$9)) -> 3 | J45: Não iniciado | K45: A Brunetto já mandou essa base no fim de 2025; agora devolve atualizada, com o aproveitamento de crédito de cada item | L45: 3. Fiscal/CST
A46: 2.26 | B46: N | C46: Comparar a base de NCM antiga da Brunetto com a nova | D46: Fernando Gomes, com Jober e Eliandra | E46: 46308 | F46: 46311 | G46: =IF(OR(E46="",F46=""),"",NETWORKDAYS(E46,F46,Feriados!$A$2:$A$9)) -> 4 | J46: Não iniciado | K46: Depende da 2.24. Base para a 2.26 (parametrizar os produtos ativos com NBS e NCM) | L46: 3. Fiscal/CST
A47: 2.27 | B47: N | C47: Parametrizar todos os produtos ativos com NBS NCM | D47: Fernando Gomes | E47: 46314 | F47: 46346 | G47: =IF(OR(E47="",F47=""),"",NETWORKDAYS(E47,F47,Feriados!$A$2:$A$9)) -> 23 | J47: Não iniciado | L47: 3. Fiscal/CST
A48: 2.28 | B48: S | C48: Acompanhar a emissão real das primeiras notas com IBS e CBS destacados | D48: Pablo | E48: 46296 | F48: 46311 | G48: =IF(OR(E48="",F48=""),"",NETWORKDAYS(E48,F48,Feriados!$A$2:$A$9)) -> 11 | J48: Não iniciado | K48: Relatado que as notas já saem com IBS e CBS no XML. Confirmar para marcar como concluída | L48: 4. TI/DF-e
A49: 2.29 | B49: N | C49: Parametrizar os layouts de nota de débito e nota de crédito | D49: Adilson Alberton | E49: 46357 | F49: 46374 | G49: =IF(OR(E49="",F49=""),"",NETWORKDAYS(E49,F49,Feriados!$A$2:$A$9)) -> 14 | J49: Não iniciado | L49: 3. Fiscal/CST
A50: 2.30 | C50: Acompanhar o enquadramento da Bogo Locações na segunda onda da NFS-e | D50: Adilson Alberton | E50: 46296 | F50: 46325 | G50: =IF(OR(E50="",F50=""),"",NETWORKDAYS(E50,F50,Feriados!$A$2:$A$9)) -> 21 | J50: Não iniciado | L50: 3. Fiscal/CST
A51: 2.31 | B51: N | C51: Avaliar custo e risco do ambiente de homologação espelhado à produção, ou propor outra estratégia para testar a virada | D51: Pablo e Kelvin | E51: 46293 | F51: 46296 | G51: =IF(OR(E51="",F51=""),"",NETWORKDAYS(E51,F51,Feriados!$A$2:$A$9)) -> 4 | H51: 46296 | I51: 46296 | J51: Concluído | L51: 4. TI/DF-e
A52: 2.32 | B52: N | C52: Parametrizar as transações com IBS e CBS (inclusive as de Suprimentos) e a integração contábil nas novas contas | D52: Juliano Liberato | E52: 46328 | F52: 46353 | G52: =IF(OR(E52="",F52=""),"",NETWORKDAYS(E52,F52,Feriados!$A$2:$A$9)) -> 18 | J52: Não iniciado | L52: 3. Fiscal/CST
A53: 2.33 | B53: N | C53: Lançar notas de teste com IBS e CBS na base de homologação, conferindo se a contabilização cai na conta correta | D53: Eliandra Fraron | E53: 46327 | F53: 46332 | G53: =IF(OR(E53="",F53=""),"",NETWORKDAYS(E53,F53,Feriados!$A$2:$A$9)) -> 4 | J53: Não iniciado | L53: 5. Contábil
A54: 2.34 | B54: N | C54: Validar o item 2.33 com nota de teste, conferindo se a contabilização cai na conta correta | D54: Juliano Liberato | E54: 46357 | F54: 46371 | G54: =IF(OR(E54="",F54=""),"",NETWORKDAYS(E54,F54,Feriados!$A$2:$A$9)) -> 11 | J54: Não iniciado | K54: Eliandra (02/10): coincide com o envio, o cadastro e a validação da alíquota oficial. Com o processo testado, é só trocar para a alíquota oficial | L54: 5. Contábil
A55: 2.35 | B55: N | C55: Testar a integração fiscal-contábil das notas de teste e conciliar o razão | D55: Eliandra Fraron | E55: 46372 | F55: 46378 | G55: =IF(OR(E55="",F55=""),"",NETWORKDAYS(E55,F55,Feriados!$A$2:$A$9)) -> 5 | J55: Não iniciado | K55: Prazo de 1 semana: testa, devolve, corrige e testa de novo. Depende das notas de teste na homologação | L55: 5. Contábil
A56: 2.36 | B56: N | C56: Carregar as alíquotas oficiais e homologar a apuração de 2027 | D56: Eliandra Fraron | E56: 46372 | F56: 46386 | G56: =IF(OR(E56="",F56=""),"",NETWORKDAYS(E56,F56,Feriados!$A$2:$A$9)) -> 10 | J56: Não iniciado | K56: Marcada para confirmar. Atenção: em janeiro a apuração de dezembro ainda é PIS e Cofins | L56: 5. Contábil
A57: 2.37 | B57: N | C57: Definir a regra da dupla nota fiscal no setor público: NF de fornecimento na medição atestada (destaque informativo no grupo gTribCompraGov, com redutor de ente) e NF de pagamento na data do recebimento, com a alíquota vigente nessa data e referenciando a NF de fornecimento | D57: Adilson Alberton | E57: 46308 | F57: 46318 | G57: =IF(OR(E57="",F57=""),"",NETWORKDAYS(E57,F57,Feriados!$A$2:$A$9)) -> 9 | J57: Não iniciado | K57: A NF de pagamento é a que gera o débito na apuração assistida. Base para a 2.38, 4.10 e 6.9 | L57: 3. Fiscal/CST
A58: 2.38 | B58: N | C58: Parametrizar no ERP Senior e no eDocs a emissão da NF de fornecimento (gTribCompraGov) e da NF de pagamento vinculada à ordem bancária | D58: Pablo e Kelvin | E58: 46321 | F58: 46353 | G58: =IF(OR(E58="",F58=""),"",NETWORKDAYS(E58,F58,Feriados!$A$2:$A$9)) -> 23 | J58: Não iniciado | K58: Depende da 2.37. Confirmar com a Senior se a funcionalidade já está liberada | L58: 4. TI/DF-e
A59: 2.39 | B59: N | C59: Testar na base de homologação o ciclo completo do setor público: medição, NF de fornecimento, ordem bancária, NF de pagamento e apuração | D59: Pablo e Adilson Alberton | E59: 46356 | F59: 46367 | G59: =IF(OR(E59="",F59=""),"",NETWORKDAYS(E59,F59,Feriados!$A$2:$A$9)) -> 10 | J59: Não iniciado | K59: Depende da 2.38. Serviço de dez/26 pago em jan/27 já cai na CBS plena | L59: 4. TI/DF-e
A60: 2.40 | B60: N | C60: Classificar a carteira de clientes por destinatário: administração direta, estatal e privado | D60: Giselle, com André Desoti | E60: 46308 | F60: 46325 | G60: =IF(OR(E60="",F60=""),"",NETWORKDAYS(E60,F60,Feriados!$A$2:$A$9)) -> 14 | J60: Não iniciado | L60: 3. Fiscal/CST
A61: 2.41 | B61: N | C61: Criar no cadastro de cliente do Senior o campo de destinatário, carregar a classificação da 2.40 e refletir no faturamento e nos relatórios de receita | D61: Pablo e Kelvin | E61: 46329 | F61: 46345 | G61: =IF(OR(E61="",F61=""),"",NETWORKDAYS(E61,F61,Feriados!$A$2:$A$9)) -> 13 | J61: Não iniciado | K61: Depende da 2.40 | L61: 4. TI/DF-e
A62: 2.42 | B62: N | C62: Validar se o monitoramento atual de rejeições de DF-e (eDocs) atende como painel do KPI de taxa de rejeição e, se não atender, propor o painel | D62: Pablo e Kelvin | E62: 46308 | F62: 46318 | G62: =IF(OR(E62="",F62=""),"",NETWORKDAYS(E62,F62,Feriados!$A$2:$A$9)) -> 9 | J62: Não iniciado | L62: 4. TI/DF-e
A63: 2.43 | B63: N | C63: Validar se a contingência de emissão da NFS-e (ambiente nacional ou prefeitura fora do ar) já existe e foi testada e, se não, testar | D63: Pablo e Kelvin | E63: 46321 | F63: 46332 | G63: =IF(OR(E63="",F63=""),"",NETWORKDAYS(E63,F63,Feriados!$A$2:$A$9)) -> 9 | J63: Não iniciado | L63: 4. TI/DF-e
A64: 3 | C64: Alteração do regime de apuração - Tarefa 102141 | E64: =MIN(E65:E68) -> 46296 | F64: =MAX(F65:F68) -> 46386 | G64: =IF(OR(E64="",F64=""),"",NETWORKDAYS(E64,F64,Feriados!$A$2:$A$9)) -> 61
A65: 3.1 | B65: N | C65: Definir o que muda na virada no faturamento e o que segue no regime atual até o fechamento de dezembro | D65: Giselle | E65: 46296 | F65: 46325 | G65: =IF(OR(E65="",F65=""),"",NETWORKDAYS(E65,F65,Feriados!$A$2:$A$9)) -> 21 | J65: Não iniciado | L65: 3. Fiscal/CST
A66: 3.2 | B66: N | C66: Parametrizar o encerramento do regime cumulativo e a apuração da CBS com crédito e nova transação e forma de contabilização | D66: Adilson Alberton | E66: 46329 | F66: 46367 | G66: =IF(OR(E66="",F66=""),"",NETWORKDAYS(E66,F66,Feriados!$A$2:$A$9)) -> 28 | J66: Não iniciado | L66: 3. Fiscal/CST
A67: 3.3 | B67: N | C67: Testar na base de homologação o fluxo do crédito de IBS e CBS na entrada (a apropriar, a compensar e encontro com o débito) | D67: Adilson Alberton e Eliandra Fraron | E67: 46370 | F67: 46374 | G67: =IF(OR(E67="",F67=""),"",NETWORKDAYS(E67,F67,Feriados!$A$2:$A$9)) -> 5 | J67: Não iniciado | K67: Apuração assistida a partir de 01/01/2027. A Receita ainda não liberou o detalhe de como operacionalizar; na prática, só em janeiro | L67: 3. Fiscal/CST
A68: 3.4 | B68: N | C68: Testar a virada em paralelo com um mês fechado | D68: Adilson Alberton | E68: 46370 | F68: 46386 | G68: =IF(OR(E68="",F68=""),"",NETWORKDAYS(E68,F68,Feriados!$A$2:$A$9)) -> 12 | J68: Não iniciado | K68: Na reunião foi dito que o mês fechado do paralelo é janeiro. Revisar as datas | L68: 3. Fiscal/CST
A69: 4 | C69: Controladoria, Fiscal e Contabilidade - Tarefa 102123 | E69: =MIN(E70:E75) -> 46296 | F69: =MAX(F70:F75) -> 46444 | G69: =IF(OR(E69="",F69=""),"",NETWORKDAYS(E69,F69,Feriados!$A$2:$A$9)) -> 100
A70: 4.1 | B70: N | C70: Confirmar por escrito o tratamento do crédito de vale-alimentação e refeição após a LC 227/2026 | D70: Aloísio Grunow | E70: 46301 | F70: 46311 | G70: =IF(OR(E70="",F70=""),"",NETWORKDAYS(E70,F70,Feriados!$A$2:$A$9)) -> 8 | J70: Não iniciado | L70: 1. Benefícios
A71: 4.2 | B71: N | C71: Entregar a lista de produtos e serviços que geram crédito de CBS | D71: Aloísio Grunow | E71: 46301 | F71: 46311 | G71: =IF(OR(E71="",F71=""),"",NETWORKDAYS(E71,F71,Feriados!$A$2:$A$9)) -> 8 | J71: Não iniciado | L71: 3. Fiscal/CST
A72: 4.3 | B72: N | C72: Definir, transação a transação, o que é creditável na entrada (depende da 4.1) | D72: Giselle | E72: =F71+3 -> 46314 | F72: 46318 | G72: =IF(OR(E72="",F72=""),"",NETWORKDAYS(E72,F72,Feriados!$A$2:$A$9)) -> 5 | J72: Não iniciado | L72: 3. Fiscal/CST
A73: 4.4 | B73: N | C73: Nomear o responsável pelo controle de créditos de IBS e CBS | D73: Juliano Liberato | E73: 46296 | F73: 46325 | G73: =IF(OR(E73="",F73=""),"",NETWORKDAYS(E73,F73,Feriados!$A$2:$A$9)) -> 21 | J73: Não iniciado | L73: 3. Fiscal/CST
A74: 4.5 | B74: N | C74: Levantar e documentar os saldos de PIS e Cofins com memória de cálculo | D74: Adilson Alberton | E74: 46296 | F74: 46356 | G74: =IF(OR(E74="",F74=""),"",NETWORKDAYS(E74,F74,Feriados!$A$2:$A$9)) -> 40 | J74: Não iniciado | L74: 5. Contábil
A75: 4.6 | B75: N | C75: Fechar a primeira apuração real de CBS | D75: Eliandra Fraron | E75: 46419 | F75: 46444 | G75: =IF(OR(E75="",F75=""),"",NETWORKDAYS(E75,F75,Feriados!$A$2:$A$9)) -> 18 | J75: Não iniciado | L75: 5. Contábil
A76: 4.7 | B76: N | C76: Adequar o plano de contas à OT CFC 1/2026 e confirmar a abertura das contas de IBS e CBS | D76: Eliandra Fraron | E76: 46308 | F76: 46325 | G76: =IF(OR(E76="",F76=""),"",NETWORKDAYS(E76,F76,Feriados!$A$2:$A$9)) -> 14 | J76: Não iniciado | K76: Pré-requisito da 2.32. A 2.31 cita que a Eliandra cria as contas no fiscal de outubro | L76: 5. Contábil
A77: 4.8 | B77: N | C77: Realizar o inventário do estoque em 31/12/2026 | D77: Eliandra Fraron, com Fernando Gomes | E77: 46357 | F77: 46387 | G77: =IF(OR(E77="",F77=""),"",NETWORKDAYS(E77,F77,Feriados!$A$2:$A$9)) -> 22 | J77: Não iniciado | K77: Atenção ao conflito com as férias coletivas a partir de 20/12 (1.4) | L77: 5. Contábil
A78: 4.9 | B78: N | C78: Concluir a consolidação da Grabin | D78: Eliandra Fraron | E78: 46357 | F78: 46387 | G78: =IF(OR(E78="",F78=""),"",NETWORKDAYS(E78,F78,Feriados!$A$2:$A$9)) -> 22 | J78: Não iniciado | K78: Confirmar o escopo com a Brunetto | L78: 5. Contábil
A79: 4.10 | B79: N | C79: Definir e testar a conciliação entre ordem bancária, NF de fornecimento, NF de pagamento e apuração | D79: Eliandra Fraron | E79: 46363 | F79: 46374 | G79: =IF(OR(E79="",F79=""),"",NETWORKDAYS(E79,F79,Feriados!$A$2:$A$9)) -> 10 | J79: Não iniciado | K79: Depende da 2.39 | L79: 5. Contábil
A80: 5 | C80: Suprimentos - Tarefa 102147 | E80: =MIN(E81:E99) -> 46266 | F80: =MAX(F81:F99) -> 46444 | G80: =IF(OR(E80="",F80=""),"",NETWORKDAYS(E80,F80,Feriados!$A$2:$A$9)) -> 122 | H80: =MIN(H81:H99) -> 46286 | I80: =MAX(I81:I99) -> 46293
A81: 5.1 | B81: N | C81: Consolidar a base de fornecedores por regime tributário e negócio: Facilities e Foods | D81: Fernando Gomes | E81: 46266 | F81: 46325 | G81: =IF(OR(E81="",F81=""),"",NETWORKDAYS(E81,F81,Feriados!$A$2:$A$9)) -> 43 | J81: Em andamento | K81: Formulário enviado aos fornecedores; nem todos responderam. Base para a 5.13 | L81: Suprimentos
A82: 5.2 | B82: N | C82: Consolidar a base de fornecedores por regime tributário e negócio: Frota | D82: Eduardo Santos | E82: 46266 | F82: 46325 | G82: =IF(OR(E82="",F82=""),"",NETWORKDAYS(E82,F82,Feriados!$A$2:$A$9)) -> 43 | J82: Em andamento | K82: Formulário enviado aos fornecedores; nem todos responderam. Base para a 5.13 | L82: Suprimentos
A83: 5.3 | B83: N | C83: Separar os fornecedores do Simples Nacional (Facilities e Foods) | D83: Fernando Gomes | E83: 46310 | F83: 46325 | G83: =IF(OR(E83="",F83=""),"",NETWORKDAYS(E83,F83,Feriados!$A$2:$A$9)) -> 12 | J83: Não iniciado | L83: Suprimentos
A84: 5.4 | B84: N | C84: Separar os fornecedores do Simples Nacional (Frota) | D84: Eduardo Santos | E84: 46293 | F84: 46325 | G84: =IF(OR(E84="",F84=""),"",NETWORKDAYS(E84,F84,Feriados!$A$2:$A$9)) -> 24 | J84: Em andamento | L84: Suprimentos
A85: 5.5 | B85: S | C85: Orientar os fornecedores estratégicos do Simples sobre a opção pelo regime regular (Facilities e Foods) | D85: Fernando Gomes | E85: 46286 | F85: 46293 | G85: =IF(OR(E85="",F85=""),"",NETWORKDAYS(E85,F85,Feriados!$A$2:$A$9)) -> 6 | H85: 46286 | I85: 46293 | J85: Concluído | L85: Suprimentos
A86: 5.6 | B86: S | C86: Orientar os fornecedores estratégicos do Simples sobre a opção pelo regime regular (Frota) | D86: Eduardo Santos | E86: 46286 | F86: 46293 | G86: =IF(OR(E86="",F86=""),"",NETWORKDAYS(E86,F86,Feriados!$A$2:$A$9)) -> 6 | H86: 46286 | I86: 46293 | J86: Concluído | L86: Suprimentos
A87: 5.7 | B87: N | C87: Levantar se é possível concentrar as compras até 20/12 (Suprimentos e Foods) | D87: Fernando Gomes | E87: 46349 | F87: 46356 | G87: =IF(OR(E87="",F87=""),"",NETWORKDAYS(E87,F87,Feriados!$A$2:$A$9)) -> 6 | J87: Não iniciado | K87: Foods, que é o maior volume, deve conseguir. Facilities tem contratos de transporte que exigem nota. Estimativa, não número exato | L87: Suprimentos
A88: 5.8 | B88: N | C88: Levantar se é possível concentrar as compras até 20/12 (Frota) | D88: Eduardo Santos | E88: 46349 | F88: 46356 | G88: =IF(OR(E88="",F88=""),"",NETWORKDAYS(E88,F88,Feriados!$A$2:$A$9)) -> 6 | J88: Não iniciado | K88: Aluguel dá para adiantar; manutenção só em parte; abastecimento e conserto emergencial não têm como | L88: Suprimentos
A89: 5.9 | B89: N | C89: Definir a data de corte de compras garantindo o recebimento até 20/12 (Suprimentos e Foods) | D89: Fernando Gomes | E89: 46357 | F89: 46357 | G89: =IF(OR(E89="",F89=""),"",NETWORKDAYS(E89,F89,Feriados!$A$2:$A$9)) -> 1 | J89: Não iniciado | K89: Depende da 5.7. Substitui a antiga 4.14 (fechamento de dezembro e corte de 31/12) | L89: Suprimentos
A90: 5.10 | B90: N | C90: Definir a data de corte de compras garantindo o recebimento até 20/12 (Frota) | D90: Eduardo Santos | E90: 46357 | F90: 46357 | G90: =IF(OR(E90="",F90=""),"",NETWORKDAYS(E90,F90,Feriados!$A$2:$A$9)) -> 1 | J90: Não iniciado | K90: Depende da 5.8 | L90: Suprimentos
A91: 5.11 | B91: N | C91: Definir com os fornecedores a rotina de recolhimento para evitar pagamento em duplicidade | D91: Brunetto e Suprimentos | E91: 46329 | F91: 46374 | G91: =IF(OR(E91="",F91=""),"",NETWORKDAYS(E91,F91,Feriados!$A$2:$A$9)) -> 33 | J91: Não iniciado | K91: Depende da reunião com a Brunetto (1.12). Não é especialidade de Suprimentos; a ferramenta da JP Balaban pode trazer essa base | L91: 5. Contábil
A92: 5.12 | B92: N | C92: Enviar ao Financeiro a lista de fornecedores com o regime tributário e o impacto de IBS e CBS de cada um | D92: Fernando Gomes e Eduardo Santos | E92: 46339 | F92: 46339 | G92: =IF(OR(E92="",F92=""),"",NETWORKDAYS(E92,F92,Feriados!$A$2:$A$9)) -> 1 | J92: Não iniciado | K92: Depois das 5.3 e 5.4. Classificação com orientação da Controladoria (Juliano Liberato). Pré-requisito da 6.2, 6.5 e 6.6 | L92: Suprimentos
A93: 5.13 | B93: N | C93: Calcular o crédito que deixaremos de aproveitar com os fornecedores do Simples não optantes | D93: Fernando Gomes | E93: 46335 | F93: 46346 | G93: =IF(OR(E93="",F93=""),"",NETWORKDAYS(E93,F93,Feriados!$A$2:$A$9)) -> 9 | J93: Não iniciado | K93: Depende da nova consulta à Receita (06/11), feita depois do comunicado de 30/10 | L93: Suprimentos
A94: 5.14 | B94: N | C94: Elaborar e publicar a política de compras por preço líquido de crédito | D94: Fernando Gomes | E94: 46372 | F94: 46387 | G94: =IF(OR(E94="",F94=""),"",NETWORKDAYS(E94,F94,Feriados!$A$2:$A$9)) -> 11 | J94: Não iniciado | K94: Depende das alíquotas oficiais (Senado, até 15/12) | L94: Suprimentos
A95: 5.15 | B95: N | C95: Renegociar os itens de maior valor da curva ABC dos fornecedores que mais compramos | D95: Fernando Gomes | E95: 46372 | F95: 46387 | G95: =IF(OR(E95="",F95=""),"",NETWORKDAYS(E95,F95,Feriados!$A$2:$A$9)) -> 11 | J95: Não iniciado | K95: A renegociação já é rotina; aqui entra o novo preço com a alíquota oficial | L95: Suprimentos
A96: 5.16 | B96: N | C96: Orientar e Acompanhar Suprimentos e Frota a lançar o IBS e a CBS da nota de entrada exatamente como vêm do fornecedor, sem ajuste manual | D96: Juliano Liberato, com Fernando Gomes e Eduardo Santos | E96: 46357 | F96: 46374 | G96: =IF(OR(E96="",F96=""),"",NETWORKDAYS(E96,F96,Feriados!$A$2:$A$9)) -> 14 | J96: Não iniciado | K96: Na apuração assistida a Receita usa o que está na nota do fornecedor; ajuste manual no lançamento não entra. Vale a partir de 01/01/2027 | L96: 3. Fiscal/CST
A97: 5.17 | B97: N | C97: Avaliar a contratação ou o desenvolvimento de ferramenta de análise de cotações por preço líquido de crédito | D97: Fernando Gomes | E97: 46329 | F97: 46339 | G97: =IF(OR(E97="",F97=""),"",NETWORKDAYS(E97,F97,Feriados!$A$2:$A$9)) -> 9 | J97: Não iniciado | L97: Suprimentos
A98: 5.18 | B98: N | C98: Revisar janela de opção do Simples dos fornecedores(Suprimentos e Foods) | D98: Fernando Gomes | E98: 46419 | F98: 46444 | G98: =IF(OR(E98="",F98=""),"",NETWORKDAYS(E98,F98,Feriados!$A$2:$A$9)) -> 18 | J98: Não iniciado | K98: Nova rodada com os fornecedores que não optaram; efeito no 2º semestre de 2027 | L98: Suprimentos
A99: 5.19 | B99: N | C99: Revisar janela de opção do Simples dos fornecedores (Frota) | D99: Eduardo Santos | E99: 46419 | F99: 46444 | G99: =IF(OR(E99="",F99=""),"",NETWORKDAYS(E99,F99,Feriados!$A$2:$A$9)) -> 18 | J99: Não iniciado | K99: Nova rodada com os fornecedores que não optaram; efeito no 2º semestre de 2027 | L99: Suprimentos
A100: 6 | C100: Financeiro - Tarefa 102137 (Split payment prorrogado para 2028) | E100: =MIN(E101:E107) -> 46296 | F100: =MAX(F101:F107) -> 46477 | G100: =IF(OR(E100="",F100=""),"",NETWORKDAYS(E100,F100,Feriados!$A$2:$A$9)) -> 123
...

Sheet Alterações 24-09
A1: Alterações da reunião com Controladoria/Fiscal (24/09/2026)
A2: DITO = decidido na reunião (fala ou edição feita na planilha durante a reunião). INFERIDO = ajuste feito na organização do arquivo, validar.
A4: ID novo | B4: ID anterior | C4: Tipo | D4: O que mudou | E4: Base
A5: 1.2 | B5: 1.2 | C5: Alterada | D5: Correção de texto: "reunões" para "reuniões" | E5: DITO
A6: 2.2 | B6: 2.2 | C6: Alterada | D6: DeRE retirada; mantida só a cobrança das APIs de apuração da CBS (saem entre outubro e novembro) | E6: DITO
A7: 2.4 | B7: 2.4 | C7: Alterada | D7: Registrado que o único problema é Medianeira (Bogo Locações), a ver com a T.I. | E7: DITO
A8: 2.8 | C8: Incluída | D8: Validar a parametrização do item 2.7. Responsável: Eliandra Fraron. Datas a definir | E8: DITO
A9: 2.9 | B9: 2.8 | C9: Alterada | D9: Passa a depender da lista de cClassTrib por cliente (7.2) | E9: DITO
A10: 2.12 | B10: 2.11 | C10: Alterada | D10: Robô diagnóstico identificado como ferramenta da Senior; ver acesso com a T.I. | E10: DITO
A11: 2.16 | B11: 2.15 | C11: Alterada | D11: Responsável: Giselle para Adilson Alberton | E11: DITO
A12: 2.17 | B12: 2.16 | C12: Alterada | D12: Retirada a "DeRE 2/2" das entregas Senior de novembro | E12: DITO
A13: 2.18 | B13: 2.17 | C13: Alterada | D13: Responsável: Kelvin para Eliandra Fraron | E13: DITO
A14: 2.19 | C14: Incluída | D14: Validar a integração contábil (2.18) com nota de teste. Responsável: Juliano Liberato. Datas a definir | E14: DITO
A15: 2.20 | B15: 2.18 | C15: Alterada | D15: Responsável: Kelvin para Eliandra Fraron. Marcada para confirmar | E15: DITO
A16: 2.3, 2.11, 2.13 | B16: 2.3, 2.10, 2.12 | C16: Status a confirmar | D16: Relatadas como já realizadas (eDocs na última versão, notas saindo com IBS e CBS). Status não alterado até confirmação | E16: DITO
A17: 3.2 | B17: 3.2 | C17: Alterada | D17: Incluída "nova transação e forma de contabilização". Responsável: Kelvin para Adilson Alberton | E17: DITO
A18: 3.3 | B18: 3.3 | C18: Alterada | D18: Responsável: Giselle para Adilson Alberton. Dito que o mês fechado do paralelo é janeiro (datas a revisar) | E18: DITO
A19: 7.13 | B19: 3.4 | C19: Movida | D19: Acompanhar o primeiro faturamento no novo regime foi para Comercial e Contratos | E19: DITO
A20: Removida | B20: 4.1 | C20: Removida | D20: Parecer sobre a DeRE: a DeRE não se aplica ao Grupo | E20: DITO
A21: 4.1 | B21: 4.2 | C21: Alterada | D21: Registrada a dependência da lista de créditos (4.3) | E21: DITO
A22: Removida | B22: 4.5 | C22: Removida | D22: Inconsistências de PIS e Cofins apontadas pela Receita: rotina, não é do projeto | E22: DITO
A23: Removida | B23: 4.6 | C23: Removida | D23: Política contábil de 2026 com a auditoria | E23: DITO
A24: Removida | B24: 4.8 | C24: Removida | D24: Centros de custo de merenda e refeição corporativa: já resolvido | E24: DITO
A25: 4.5 | B25: 4.9 | C25: A confirmar | D25: Contas de IBS e CBS provavelmente já abertas no plano de contas | E25: DITO
A26: Removida | B26: 4.11 | C26: Removida | D26: Mapear editais com exigência de índices ou faturamento mínimo | E26: DITO
... A34: 7.1 | B34: 7.1 | C34: Alterada | D34: Responsável: André Desoti para Clayton. Ordem 1 | E34: DITO
A35: 7.2 | C35: Incluída | D35: Lista de cClassTrib por serviço e por cliente (todos). André Desoti. Urgente (ordem 1.1) | E35: DITO
A36: 7.3 | B36: 7.4 | C36: Alterada | D36: Responsável: Ingrid Perez para André Desoti. Confirmar se é o mesmo documento da 7.4 | E36: DITO
A37: 7.4 | C37: Incluída | D37: Preparar o modelo de pedido de reequilíbrio para contratos públicos. André Desoti | E37: DITO
A38: 7.7 | B38: 7.8 | C38: Alterada | D38: De "pilotos de 5 a 10 contratos" para todos os contratos | E38: DITO
A39: 7.9 | B39: 7.2 | C39: Alterada | D39: De "clientes privados" para 100% dos clientes; passa a vir depois do protocolo | E39: DITO
A40: 7.10 | B40: 7.6 | C40: Alterada | D40: De "assinar os aditivos dos clientes privados" para monitorar a assinatura de aditivos e reequilíbrios de 100% dos clientes | E40: DITO
A41: 7.11 | C41: Incluída | D41: Avaliar antecipar o faturamento para dezembro. Kairon Riguete | E41: DITO
A42: 7.12 | C42: Incluída | D42: Validar as alíquotas de CBS com o faturamento antes do início do faturamento de 01/2027. André Desoti | E42: DITO
A43: 7.14 | B43: 7.5 | C43: Reordenada | D43: Simulação da carteira marcada como n/a na ordem. Confirmar se sai | E43: DITO
A44: Seção 7 | B44: Seção 7 | C44: Reordenada | D44: Seção reordenada pela sequência definida na reunião (coluna Observação traz a ordem) | E44: DITO

Sheet Marcos externos
A1: Marcos externos
A2: Datas definidas por lei, ato normativo ou fornecedor, fora do controle do projeto
A4: ID | B4: Data | C4: Marco | D4: Fonte | E4: Quem define | F4: Atividades vinculadas | G4: Dias até o marco
A5: E01 | B5: 46295 | C5: Fim da janela de opção pelo Simples e pelo regime regular de IBS e CBS para o 1º semestre de 2027 | D5: Resoluções CGSN 190 e 191/2026 | E5: Fornecedores do Simples | F5: S03 | G5: =IF(B5<#REF!,"Passado",B5-#REF!) -> #REF!
A6: E02 | B6: 46296 | C6: NFS-e com destaque obrigatório de IBS e CBS | D6: Ato Conjunto RFB/CGIBS nº 4/2026 | E6: Receita Federal e CGIBS | F6: T11, T12, T13 | G6: =IF(B6<#REF!,"Passado",B6-#REF!) -> #REF!
A7: E03 | B7: 46296 | C7: DeRE passa a receber os eventos de tabela do contribuinte | D7: Comunicado SPED | E7: Receita Federal | F7: Não se aplica (DeRE fora do escopo) | G7: =IF(B7<#REF!,"Passado",B7-#REF!) -> #REF!
A8: E04 | B8: 46300 | C8: API de apuração da CBS: consulta de débitos e créditos (início de outubro) | D8: Documentação técnica RFB de 14/09/2026 | E8: Receita Federal | F8: T02 | G8: =IF(B8<#REF!,"Passado",B8-#REF!) -> #REF!
A9: E05 | B9: 46325 | C9: Publicação dos leiautes de nota de débito e nota de crédito (previsão) | D9: Reunião de TI | E9: Receita Federal e CGIBS | F9: T15 | G9: =IF(B9<#REF!,"Passado",B9-#REF!) -> #REF!
A10: E06 | B10: 46325 | C10: Cálculos do TCU encaminhados ao Senado | D10: Prazos da alíquota de referência prorrogados em 45 dias | E10: TCU | G10: =IF(B10<#REF!,"Passado",B10-#REF!) -> #REF!
A11: E07 | B11: 46329 | C11: API de apuração da CBS: pagamentos e recolhimentos pelo adquirente (início de novembro) | D11: Documentação técnica RFB de 14/09/2026 | E11: Receita Federal | G11: =IF(B11<#REF!,"Passado",B11-#REF!) -> #REF!
A12: E08 | B12: 46336 | C12: Prazo para correção das inconsistências de PIS e Cofins apontadas pela Receita | D12: Memorando Contábil 18/09 | E12: Receita Federal | F12: Atividade removida na reunião | G12: =IF(B12<#REF!,"Passado",B12-#REF!) -> #REF!
A13: E09 | B13: 46339 | C13: Primeira entrega mensal da DeRE, competência outubro (prazo legal 15/11, domingo) | D13: Comunicado SPED | E13: Receita Federal | F13: Não se aplica (DeRE fora do escopo) | G13: =IF(B13<#REF!,"Passado",B13-#REF!) -> #REF!
A14: E10 | B14: 46356 | C14: Prazo para o fornecedor cancelar a opção feita em setembro | D14: Resoluções CGSN 190 e 191/2026 | E14: Fornecedores do Simples | F14: S05 | G14: =IF(B14<#REF!,"Passado",B14-#REF!) -> #REF!
A15: E11 | B15: 46356 | C15: Entregas Senior de novembro: split payment, conciliação da apuração, DeRE 2/2 | D15: Calendário de liberações Senior | E15: Senior | F15: T17 | G15: =IF(B15<#REF!,"Passado",B15-#REF!) -> #REF!
A16: E12 | B16: 46356 | C16: API de apuração da CBS: emissão de DARF RAD e PCONT (fim de novembro) | D16: Documentação técnica RFB de 14/09/2026 | E16: Receita Federal | F16: F02 | G16: =IF(B16<#REF!,"Passado",B16-#REF!) -> #REF!
A17: E13 | B17: 46357 | C17: Segunda onda da NFS-e, incluindo locações | D17: Ato Conjunto RFB/CGIBS nº 4/2026 | E17: Receita Federal e CGIBS | F17: T16 | G17: =IF(B17<#REF!,"Passado",B17-#REF!) -> #REF!
A18: E14 | B18: 46371 | C18: Prazo máximo para definição da alíquota de referência pelo Senado | D18: Prazos da alíquota de referência prorrogados em 45 dias | E18: Senado Federal | F18: T20, K06 | G18: =IF(B18<#REF!,"Passado",B18-#REF!) -> #REF!
A19: E15 | B19: 46387 | C19: Fim do PIS e da Cofins e fim da tolerância de não rejeição da NFS-e sem IBS e CBS | D19: LC 214/2025 e Ato Conjunto RFB/CGIBS nº 4/2026 | E19: Receita Federal | F19: K13 | G19: =IF(B19<#REF!,"Passado",B19-#REF!) -> #REF!
A20: E16 | B20: 46447 | C20: Nova janela de opção do Simples, com efeito no 2º semestre de 2027 | D20: Resoluções CGSN 190 e 191/2026 | E20: Fornecedores do Simples | F20: S09 | G20: =IF(B20<#REF!,"Passado",B20-#REF!) -> #REF!
A21: E17 | B21: 46569 | C21: Split payment facultativo, somente entre empresas (informado na reunião como prorrogado para 2028; confirmar o ato) | D21: Memorando ERP 18/09 | E21: Receita Federal e CGIBS | F21: F08 | G21: =IF(B21<#REF!,"Passado",B21-#REF!) -> #REF!

Sheet Premissas
A1: Premissas
A3: Nº | B3: Premissa
A4: 1 | B4: Datas legais conforme os atos publicados até 18/09/2026.
A5: 2 | B5: Datas internas propostas, sujeitas à validação com Kairon Riguete.
A6: 3 | B6: Prazos que caíam em fim de semana ou feriado foram antecipados para o dia útil anterior.
A7: 4 | B7: Reunião semanal de status às sextas-feiras, com as principais lideranças.
A8: 5 | B8: Equipe de TI e Controladoria trabalhando em sala dedicada, em blocos diários.
A9: 6 | B9: Melhorias e customizações de TI suspensas; suporte à operação e ao faturamento mantidos.
A10: 7 | B10: Fechamento de dezembro de 2026 no regime atual; novo regime aplicado a partir da virada.
A11: 8 | B11: Split payment informado na reunião de 24/09 como prorrogado para 2028 (confirmar o ato); fora do horizonte deste cronograma.
A12: 9 | B12: Automação da separação de documentos por cliente tratada no projeto de IA corporativa.
A13: 10 | B13: Contrato da JP Balaban pendente de assinatura; atividades da consultoria condicionadas à assinatura.
A14: 11 | B14: Horizonte do cronograma: 21/09/2026 a 31/03/2027.
A15: 12 | B15: DeRE não se aplica às empresas do Grupo (decisão da reunião de 24/09).
A16: 13 | B16: Datas das atividades novas ou sem data serão confirmadas com cada área responsável.

Sheet Feriados
A1: Data | B1: Feriado
A2: 46307 | B2: Nossa Senhora Aparecida
A3: 46328 | B3: Finados
A4: 46341 | B4: Proclamação da República
A5: 46346 | B5: Dia da Consciência Negra
A6: 46381 | B6: Natal
A7: 46388 | B7: Confraternização Universal
A8: 46433 | B8: Carnaval
A9: 46434 | B9: Carnaval
